cactus/__init__.py
cactus/appfactory.py
cactus/flask.py
cactus/functions.py
cactus/route_info.py
cactus/settings.py
cactus/webapp.py
pycactus-0.3.0.dist-info/LICENSE
pycactus-0.3.0.dist-info/METADATA
pycactus-0.3.0.dist-info/WHEEL
pycactus-0.3.0.dist-info/top_level.txt
pycactus-0.3.0.dist-info/RECORD
