Metadata-Version: 2.1
Name: pycactus
Version: 0.3.0
Summary: Adapter to run an Azure Function Application with a WSGI Web Server.
Home-page: https://github.com/Claudjos/cactus
Author: Claudjos
Author-email: claudjosmail@gmail.com
License: UNKNOWN
Keywords: Azure Function,Web App
Platform: UNKNOWN
License-File: LICENSE
Requires-Dist: azure-functions
Provides-Extra: flask
Requires-Dist: flask ; extra == 'flask'
